baiji/__init__.py
baiji/sdk.py
baiji/clients/__init__.py
baiji/clients/generic.py
baiji/clients/resource.py
baiji_sdk-1.1.0.dist-info/LICENSE
baiji_sdk-1.1.0.dist-info/METADATA
baiji_sdk-1.1.0.dist-info/WHEEL
baiji_sdk-1.1.0.dist-info/top_level.txt
baiji_sdk-1.1.0.dist-info/RECORD
